furs_fiscal/__init__.py
furs_fiscal/api.py
furs_fiscal/base_api.py
furs_fiscal/connector.py
furs_fiscal/exceptions.py
furs_fiscal/certs/test_certificate.pem
furs_fiscal-1.1.0.dist-info/LICENSE
furs_fiscal-1.1.0.dist-info/METADATA
furs_fiscal-1.1.0.dist-info/WHEEL
furs_fiscal-1.1.0.dist-info/top_level.txt
furs_fiscal-1.1.0.dist-info/RECORD
