Metadata-Version: 2.1
Name: furs-fiscal
Version: 1.1.0
Summary: Python library for simplified communication with FURS (Financna uprava Republike Slovenije).
Home-page: https://github.com/boris-savic/python_furs_fiscal
Download-URL: https://github.com/boris-savic/python_furs_fiscal/tarball/1.1.0
Author: Boris Savic
Author-email: boris70@gmail.com
Keywords: FURS,fiscal,fiscal register,davcne blagajne
License-File: LICENSE
Requires-Dist: pytz (>=2017.2)
Requires-Dist: requests (>=2.20.0)
Requires-Dist: PyJWT (>=2.8.0)
Requires-Dist: pyOpenSSL (>=17.5.0)
